openapi_to_fastapi/__init__.py
openapi_to_fastapi/cli.py
openapi_to_fastapi/logger.py
openapi_to_fastapi/model_generator.py
openapi_to_fastapi/models.py
openapi_to_fastapi/parser.py
openapi_to_fastapi/pydantic_validators.py
openapi_to_fastapi/routes.py
openapi_to_fastapi/tests/__init__.py
openapi_to_fastapi/tests/__snapshots__/test_router/test_custom_route_definitions.json
openapi_to_fastapi/tests/__snapshots__/test_router/test_validation[bool-as-int].json
openapi_to_fastapi/tests/__snapshots__/test_router/test_validation[bool-as-null].1.json
openapi_to_fastapi/tests/__snapshots__/test_router/test_validation[bool-as-null].json
openapi_to_fastapi/tests/__snapshots__/test_router/test_validation[bool-as-random-text].1.json
openapi_to_fastapi/tests/__snapshots__/test_router/test_validation[bool-as-random-text].json
openapi_to_fastapi/tests/__snapshots__/test_router/test_validation[bool-as-string].json
openapi_to_fastapi/tests/__snapshots__/test_router/test_validation[date-as-month-00].1.json
openapi_to_fastapi/tests/__snapshots__/test_router/test_validation[date-as-month-00].json
openapi_to_fastapi/tests/__snapshots__/test_router/test_validation[date-as-month].1.json
openapi_to_fastapi/tests/__snapshots__/test_router/test_validation[date-as-month].json
openapi_to_fastapi/tests/__snapshots__/test_router/test_validation[date-as-unixtimestamp-day].json
openapi_to_fastapi/tests/__snapshots__/test_router/test_validation[date-as-unixtimestamp-offset0].1.json
openapi_to_fastapi/tests/__snapshots__/test_router/test_validation[date-as-unixtimestamp-offset0].json
openapi_to_fastapi/tests/__snapshots__/test_router/test_validation[date-as-unixtimestamp-offset1].1.json
openapi_to_fastapi/tests/__snapshots__/test_router/test_validation[date-as-unixtimestamp-offset1].json
openapi_to_fastapi/tests/__snapshots__/test_router/test_validation[date-as-unixtimestamp-str-day].json
openapi_to_fastapi/tests/__snapshots__/test_router/test_validation[datetime-as-unixtimestamp-day].json
openapi_to_fastapi-0.22.0.dist-info/LICENSE
openapi_to_fastapi-0.22.0.dist-info/METADATA
openapi_to_fastapi-0.22.0.dist-info/WHEEL
openapi_to_fastapi-0.22.0.dist-info/entry_points.txt
openapi_to_fastapi-0.22.0.dist-info/RECORD
