Metadata-Version: 2.1
Name: openapi-to-fastapi
Version: 0.22.0
Summary: Create FastAPI routes from OpenAPI spec
Home-page: https://github.com/ioxiocom/openapi-to-fastapi
License: BSD-3-Clause
Author: IOXIO Ltd
Requires-Python: >=3.10,<4.0
Classifier: License :: OSI Approved :: BSD License
Classifier: Programming Language :: Python :: 3
Classifier: Programming Language :: Python :: 3.10
Classifier: Programming Language :: Python :: 3.11
Classifier: Programming Language :: Python :: 3.12
Classifier: Programming Language :: Python :: 3.13
Requires-Dist: click (>=8.3.0,<9.0.0)
Requires-Dist: coloredlogs (>=15.0.1,<16.0.0)
Requires-Dist: datamodel-code-generator (>=0.35.0,<0.36.0)
Requires-Dist: fastapi (>=0.121.1,<0.122.0)
Requires-Dist: pydantic[email] (>=2.12.4,<3.0.0)
Project-URL: Repository, https://github.com/ioxiocom/openapi-to-fastapi
